{
  "name": "N",
  "subject": 5,
  "date": null,
  "paths": {
    "Finger": {
      "strokes":
    [
      {
        "x": -99.38936249139115,
        "y": -712.6307266627199,
        "z": null,
        "alpha": null,
        "beta": null,
        "gamma": null,
        "t": 1540293519593,
        "stroke_id": 0
      },
      {
        "x": -98.28477262080395,
        "y": -711.6298921988008,
        "z": null,
        "alpha": null,
        "beta": null,
        "gamma": null,
        "t": 1540293519634,
        "stroke_id": 0
      },
      {
        "x": -98.00074389410116,
        "y": -710.1666368934013,
        "z": null,
        "alpha": null,
        "beta": null,
        "gamma": null,
        "t": 1540293519645,
        "stroke_id": 0
      },
      {
        "x": -97.43388960952825,
        "y": -707.239448246178,
        "z": null,
        "alpha": null,
        "beta": null,
        "gamma": null,
        "t": 1540293519658,
        "stroke_id": 0
      },
      {
        "x": -97.00844810389037,
        "y": -705.0442262698665,
        "z": null,
        "alpha": null,
        "beta": null,
        "gamma": null,
        "t": 1540293519673,
        "stroke_id": 0
      },
      {
        "x": -98.22533205485402,
        "y": -701.92348457417,
        "z": null,
        "alpha": null,
        "beta": null,
        "gamma": null,
        "t": 1540293519690,
        "stroke_id": 0
      },
      {
        "x": -103.93099627395395,
        "y": -691.4031732741059,
        "z": null,
        "alpha": null,
        "beta": null,
        "gamma": null,
        "t": 1540293519707,
        "stroke_id": 0
      },
      {
        "x": -106.27616970290876,
        "y": -685.482697945258,
        "z": null,
        "alpha": null,
        "beta": null,
        "gamma": null,
        "t": 1540293519723,
        "stroke_id": 0
      },
      {
        "x": -110.39898423982103,
        "y": -670.7133554715062,
        "z": null,
        "alpha": null,
        "beta": null,
        "gamma": null,
        "t": 1540293519739,
        "stroke_id": 0
      },
      {
        "x": -111.99703006416823,
        "y": -662.5078605245419,
        "z": null,
        "alpha": null,
        "beta": null,
        "gamma": null,
        "t": 1540293519756,
        "stroke_id": 0
      },
      {
        "x": -114.64142836198539,
        "y": -645.5961143804411,
        "z": null,
        "alpha": null,
        "beta": null,
        "gamma": null,
        "t": 1540293519773,
        "stroke_id": 0
      },
      {
        "x": -117.3301062920568,
        "y": -635.9643434639199,
        "z": null,
        "alpha": null,
        "beta": null,
        "gamma": null,
        "t": 1540293519791,
        "stroke_id": 0
      },
      {
        "x": -124.34978760880117,
        "y": -615.7752819114919,
        "z": null,
        "alpha": null,
        "beta": null,
        "gamma": null,
        "t": 1540293519807,
        "stroke_id": 0
      },
      {
        "x": -128.39796543760394,
        "y": -603.7540579337615,
        "z": null,
        "alpha": null,
        "beta": null,
        "gamma": null,
        "t": 1540293519823,
        "stroke_id": 0
      },
      {
        "x": -135.85162693369446,
        "y": -579.533217863523,
        "z": null,
        "alpha": null,
        "beta": null,
        "gamma": null,
        "t": 1540293519840,
        "stroke_id": 0
      },
      {
        "x": -138.61494157187536,
        "y": -567.1533284509803,
        "z": null,
        "alpha": null,
        "beta": null,
        "gamma": null,
        "t": 1540293519856,
        "stroke_id": 0
      },
      {
        "x": -145.0677686040468,
        "y": -544.037078251329,
        "z": null,
        "alpha": null,
        "beta": null,
        "gamma": null,
        "t": 1540293519873,
        "stroke_id": 0
      },
      {
        "x": -148.29418212013252,
        "y": -532.4789531515034,
        "z": null,
        "alpha": null,
        "beta": null,
        "gamma": null,
        "t": 1540293519890,
        "stroke_id": 0
      },
      {
        "x": -156.13562774959394,
        "y": -511.8267927211707,
        "z": null,
        "alpha": null,
        "beta": null,
        "gamma": null,
        "t": 1540293519908,
        "stroke_id": 0
      },
      {
        "x": -159.28740455757017,
        "y": -503.0167861173664,
        "z": null,
        "alpha": null,
        "beta": null,
        "gamma": null,
        "t": 1540293519923,
        "stroke_id": 0
      },
      {
        "x": -163.43933779304106,
        "y": -493.10098647414225,
        "z": null,
        "alpha": null,
        "beta": null,
        "gamma": null,
        "t": 1540293519940,
        "stroke_id": 0
      },
      {
        "x": -169.66757666445963,
        "y": -478.22788859372235,
        "z": null,
        "alpha": null,
        "beta": null,
        "gamma": null,
        "t": 1540293519957,
        "stroke_id": 0
      },
      {
        "x": -172.10254773521956,
        "y": -471.98572716590473,
        "z": null,
        "alpha": null,
        "beta": null,
        "gamma": null,
        "t": 1540293519974,
        "stroke_id": 0
      },
      {
        "x": -176.43355112189244,
        "y": -461.4284365299982,
        "z": null,
        "alpha": null,
        "beta": null,
        "gamma": null,
        "t": 1540293519990,
        "stroke_id": 0
      },
      {
        "x": -178.47219938557316,
        "y": -457.84459595639674,
        "z": null,
        "alpha": null,
        "beta": null,
        "gamma": null,
        "t": 1540293520007,
        "stroke_id": 0
      },
      {
        "x": -181.3174510282753,
        "y": -451.37122410783894,
        "z": null,
        "alpha": null,
        "beta": null,
        "gamma": null,
        "t": 1540293520024,
        "stroke_id": 0
      },
      {
        "x": -182.4080831339995,
        "y": -449.94494813828203,
        "z": null,
        "alpha": null,
        "beta": null,
        "gamma": null,
        "t": 1540293520040,
        "stroke_id": 0
      },
      {
        "x": -183.22864427788392,
        "y": -449.4825272968016,
        "z": null,
        "alpha": null,
        "beta": null,
        "gamma": null,
        "t": 1540293520057,
        "stroke_id": 0
      },
      {
        "x": -183.08723149894885,
        "y": -448.75056062588965,
        "z": null,
        "alpha": null,
        "beta": null,
        "gamma": null,
        "t": 1540293520074,
        "stroke_id": 0
      },
      {
        "x": -185.97676277390528,
        "y": -449.5571640049111,
        "z": null,
        "alpha": null,
        "beta": null,
        "gamma": null,
        "t": 1540293520091,
        "stroke_id": 0
      },
      {
        "x": -187.90311695720956,
        "y": -450.09489959092537,
        "z": null,
        "alpha": null,
        "beta": null,
        "gamma": null,
        "t": 1540293520108,
        "stroke_id": 0
      },
      {
        "x": -192.14360945718897,
        "y": -454.73905040285973,
        "z": null,
        "alpha": null,
        "beta": null,
        "gamma": null,
        "t": 1540293520125,
        "stroke_id": 0
      },
      {
        "x": -193.532228054479,
        "y": -457.2031401721782,
        "z": null,
        "alpha": null,
        "beta": null,
        "gamma": null,
        "t": 1540293520141,
        "stroke_id": 0
      },
      {
        "x": -195.6528133226809,
        "y": -459.52581716256174,
        "z": null,
        "alpha": null,
        "beta": null,
        "gamma": null,
        "t": 1540293520158,
        "stroke_id": 0
      },
      {
        "x": -199.54980132154373,
        "y": -467.8812635621696,
        "z": null,
        "alpha": null,
        "beta": null,
        "gamma": null,
        "t": 1540293520179,
        "stroke_id": 0
      },
      {
        "x": -204.8354079176965,
        "y": -478.70079973109597,
        "z": null,
        "alpha": null,
        "beta": null,
        "gamma": null,
        "t": 1540293520200,
        "stroke_id": 0
      },
      {
        "x": -207.34377731926935,
        "y": -484.59215636138515,
        "z": null,
        "alpha": null,
        "beta": null,
        "gamma": null,
        "t": 1540293520208,
        "stroke_id": 0
      },
      {
        "x": -211.2256043844365,
        "y": -490.5211703639414,
        "z": null,
        "alpha": null,
        "beta": null,
        "gamma": null,
        "t": 1540293520225,
        "stroke_id": 0
      },
      {
        "x": -217.63096178487217,
        "y": -504.7679733938385,
        "z": null,
        "alpha": null,
        "beta": null,
        "gamma": null,
        "t": 1540293520242,
        "stroke_id": 0
      },
      {
        "x": -220.4233599131478,
        "y": -512.1225853295272,
        "z": null,
        "alpha": null,
        "beta": null,
        "gamma": null,
        "t": 1540293520259,
        "stroke_id": 0
      },
      {
        "x": -226.02211393456201,
        "y": -529.2589196343807,
        "z": null,
        "alpha": null,
        "beta": null,
        "gamma": null,
        "t": 1540293520276,
        "stroke_id": 0
      },
      {
        "x": -228.6870570487656,
        "y": -538.3086753326335,
        "z": null,
        "alpha": null,
        "beta": null,
        "gamma": null,
        "t": 1540293520291,
        "stroke_id": 0
      },
      {
        "x": -232.76973745881776,
        "y": -554.6760636307325,
        "z": null,
        "alpha": null,
        "beta": null,
        "gamma": null,
        "t": 1540293520308,
        "stroke_id": 0
      },
      {
        "x": -234.83016891618138,
        "y": -562.1720883453563,
        "z": null,
        "alpha": null,
        "beta": null,
        "gamma": null,
        "t": 1540293520325,
        "stroke_id": 0
      },
      {
        "x": -239.23453542520332,
        "y": -578.6292742852604,
        "z": null,
        "alpha": null,
        "beta": null,
        "gamma": null,
        "t": 1540293520341,
        "stroke_id": 0
      },
      {
        "x": -243.1315234240661,
        "y": -586.9847206848682,
        "z": null,
        "alpha": null,
        "beta": null,
        "gamma": null,
        "t": 1540293520358,
        "stroke_id": 0
      },
      {
        "x": -247.0727910551832,
        "y": -602.6201423120552,
        "z": null,
        "alpha": null,
        "beta": null,
        "gamma": null,
        "t": 1540293520376,
        "stroke_id": 0
      },
      {
        "x": -249.04342487074177,
        "y": -610.4378531256488,
        "z": null,
        "alpha": null,
        "beta": null,
        "gamma": null,
        "t": 1540293520392,
        "stroke_id": 0
      },
      {
        "x": -253.94786959351097,
        "y": -626.342142545843,
        "z": null,
        "alpha": null,
        "beta": null,
        "gamma": null,
        "t": 1540293520410,
        "stroke_id": 0
      },
      {
        "x": -256.6128127077145,
        "y": -635.3918982440958,
        "z": null,
        "alpha": null,
        "beta": null,
        "gamma": null,
        "t": 1540293520426,
        "stroke_id": 0
      },
      {
        "x": -258.3145787302659,
        "y": -644.1727861493414,
        "z": null,
        "alpha": null,
        "beta": null,
        "gamma": null,
        "t": 1540293520443,
        "stroke_id": 0
      },
      {
        "x": -263.9133327516802,
        "y": -661.3091204541948,
        "z": null,
        "alpha": null,
        "beta": null,
        "gamma": null,
        "t": 1540293520458,
        "stroke_id": 0
      },
      {
        "x": -267.54145295753585,
        "y": -670.6277439454549,
        "z": null,
        "alpha": null,
        "beta": null,
        "gamma": null,
        "t": 1540293520475,
        "stroke_id": 0
      },
      {
        "x": -275.06656116225435,
        "y": -688.3018138363226,
        "z": null,
        "alpha": null,
        "beta": null,
        "gamma": null,
        "t": 1540293520492,
        "stroke_id": 0
      },
      {
        "x": -278.96354916111716,
        "y": -696.6572602359304,
        "z": null,
        "alpha": null,
        "beta": null,
        "gamma": null,
        "t": 1540293520508,
        "stroke_id": 0
      },
      {
        "x": -285.5254802741835,
        "y": -714.062462333791,
        "z": null,
        "alpha": null,
        "beta": null,
        "gamma": null,
        "t": 1540293520525,
        "stroke_id": 0
      },
      {
        "x": -289.6913360660535,
        "y": -721.4547316417468,
        "z": null,
        "alpha": null,
        "beta": null,
        "gamma": null,
        "t": 1540293520542,
        "stroke_id": 0
      },
      {
        "x": -298.1644604287285,
        "y": -736.9712369285701,
        "z": null,
        "alpha": null,
        "beta": null,
        "gamma": null,
        "t": 1540293520558,
        "stroke_id": 0
      },
      {
        "x": -302.1512460693964,
        "y": -745.0049972292081,
        "z": null,
        "alpha": null,
        "beta": null,
        "gamma": null,
        "t": 1540293520575,
        "stroke_id": 0
      },
      {
        "x": -310.4829576531364,
        "y": -759.7895358451194,
        "z": null,
        "alpha": null,
        "beta": null,
        "gamma": null,
        "t": 1540293520593,
        "stroke_id": 0
      },
      {
        "x": -314.68647081727323,
        "y": -765.8083474894808,
        "z": null,
        "alpha": null,
        "beta": null,
        "gamma": null,
        "t": 1540293520609,
        "stroke_id": 0
      },
      {
        "x": -322.8616086883825,
        "y": -777.4344870374287,
        "z": null,
        "alpha": null,
        "beta": null,
        "gamma": null,
        "t": 1540293520627,
        "stroke_id": 0
      },
      {
        "x": -325.9077136759696,
        "y": -781.3994894844136,
        "z": null,
        "alpha": null,
        "beta": null,
        "gamma": null,
        "t": 1540293520642,
        "stroke_id": 0
      },
      {
        "x": -331.1781593384268,
        "y": -789.7925932562883,
        "z": null,
        "alpha": null,
        "beta": null,
        "gamma": null,
        "t": 1540293520660,
        "stroke_id": 0
      },
      {
        "x": -333.38854224843385,
        "y": -791.7935841477021,
        "z": null,
        "alpha": null,
        "beta": null,
        "gamma": null,
        "t": 1540293520676,
        "stroke_id": 0
      },
      {
        "x": -337.5252793417451,
        "y": -794.3323106251302,
        "z": null,
        "alpha": null,
        "beta": null,
        "gamma": null,
        "t": 1540293520694,
        "stroke_id": 0
      },
      {
        "x": -338.6298692123324,
        "y": -795.3331450890491,
        "z": null,
        "alpha": null,
        "beta": null,
        "gamma": null,
        "t": 1540293520710,
        "stroke_id": 0
      },
      {
        "x": -338.6298692123324,
        "y": -795.3331450890491,
        "z": null,
        "alpha": null,
        "beta": null,
        "gamma": null,
        "t": 1540293520727,
        "stroke_id": 0
      },
      {
        "x": -339.4516335250494,
        "y": -794.8700462111444,
        "z": null,
        "alpha": null,
        "beta": null,
        "gamma": null,
        "t": 1540293520763,
        "stroke_id": 0
      },
      {
        "x": -339.6307036762514,
        "y": -794.228555218462,
        "z": null,
        "alpha": null,
        "beta": null,
        "gamma": null,
        "t": 1540293520776,
        "stroke_id": 0
      },
      {
        "x": -340.13078188999884,
        "y": -793.675658698752,
        "z": null,
        "alpha": null,
        "beta": null,
        "gamma": null,
        "t": 1540293520793,
        "stroke_id": 0
      },
      {
        "x": -342.4382979466867,
        "y": -789.1286410334985,
        "z": null,
        "alpha": null,
        "beta": null,
        "gamma": null,
        "t": 1540293520810,
        "stroke_id": 0
      },
      {
        "x": -343.2449013257081,
        "y": -786.2391097585421,
        "z": null,
        "alpha": null,
        "beta": null,
        "gamma": null,
        "t": 1540293520827,
        "stroke_id": 0
      },
      {
        "x": -346.21760798248226,
        "y": -778.0705941474203,
        "z": null,
        "alpha": null,
        "beta": null,
        "gamma": null,
        "t": 1540293520843,
        "stroke_id": 0
      },
      {
        "x": -347.0090504278081,
        "y": -772.7546304754121,
        "z": null,
        "alpha": null,
        "beta": null,
        "gamma": null,
        "t": 1540293520860,
        "stroke_id": 0
      },
      {
        "x": -350.69856282179853,
        "y": -762.0182696883037,
        "z": null,
        "alpha": null,
        "beta": null,
        "gamma": null,
        "t": 1540293520876,
        "stroke_id": 0
      },
      {
        "x": -351.84867070193667,
        "y": -755.4174428256738,
        "z": null,
        "alpha": null,
        "beta": null,
        "gamma": null,
        "t": 1540293520894,
        "stroke_id": 0
      },
      {
        "x": -356.972319702768,
        "y": -739.5435104813348,
        "z": null,
        "alpha": null,
        "beta": null,
        "gamma": null,
        "t": 1540293520910,
        "stroke_id": 0
      },
      {
        "x": -359.80241041177453,
        "y": -730.6437062357254,
        "z": null,
        "alpha": null,
        "beta": null,
        "gamma": null,
        "t": 1540293520927,
        "stroke_id": 0
      },
      {
        "x": -366.14294336356943,
        "y": -711.6490321956898,
        "z": null,
        "alpha": null,
        "beta": null,
        "gamma": null,
        "t": 1540293520944,
        "stroke_id": 0
      },
      {
        "x": -368.83162129364086,
        "y": -702.0172612791685,
        "z": null,
        "alpha": null,
        "beta": null,
        "gamma": null,
        "t": 1540293520961,
        "stroke_id": 0
      },
      {
        "x": -374.2089771537837,
        "y": -682.7537194461257,
        "z": null,
        "alpha": null,
        "beta": null,
        "gamma": null,
        "t": 1540293520977,
        "stroke_id": 0
      },
      {
        "x": -376.8976550838551,
        "y": -673.1219485296043,
        "z": null,
        "alpha": null,
        "beta": null,
        "gamma": null,
        "t": 1540293520993,
        "stroke_id": 0
      },
      {
        "x": -382.5590396707008,
        "y": -655.321662001961,
        "z": null,
        "alpha": null,
        "beta": null,
        "gamma": null,
        "t": 1540293521011,
        "stroke_id": 0
      },
      {
        "x": -385.24771760077226,
        "y": -645.6898910854397,
        "z": null,
        "alpha": null,
        "beta": null,
        "gamma": null,
        "t": 1540293521027,
        "stroke_id": 0
      },
      {
        "x": -391.26656445359754,
        "y": -626.605419403599,
        "z": null,
        "alpha": null,
        "beta": null,
        "gamma": null,
        "t": 1540293521045,
        "stroke_id": 0
      },
      {
        "x": -394.4183412615737,
        "y": -617.7954127997947,
        "z": null,
        "alpha": null,
        "beta": null,
        "gamma": null,
        "t": 1540293521060,
        "stroke_id": 0
      },
      {
        "x": -397.57011806954995,
        "y": -608.9854061959904,
        "z": null,
        "alpha": null,
        "beta": null,
        "gamma": null,
        "t": 1540293521078,
        "stroke_id": 0
      },
      {
        "x": -403.87299364907796,
        "y": -591.3641898195492,
        "z": null,
        "alpha": null,
        "beta": null,
        "gamma": null,
        "t": 1540293521094,
        "stroke_id": 0
      },
      {
        "x": -407.0247704570543,
        "y": -582.5541832157448,
        "z": null,
        "alpha": null,
        "beta": null,
        "gamma": null,
        "t": 1540293521112,
        "stroke_id": 0
      },
      {
        "x": -413.0587782435751,
        "y": -565.8961439309558,
        "z": null,
        "alpha": null,
        "beta": null,
        "gamma": null,
        "t": 1540293521127,
        "stroke_id": 0
      },
      {
        "x": -415.9416872585442,
        "y": -558.0493144188035,
        "z": null,
        "alpha": null,
        "beta": null,
        "gamma": null,
        "t": 1540293521145,
        "stroke_id": 0
      },
      {
        "x": -421.43795945905083,
        "y": -543.3176293173187,
        "z": null,
        "alpha": null,
        "beta": null,
        "gamma": null,
        "t": 1540293521162,
        "stroke_id": 0
      },
      {
        "x": -423.78313288800564,
        "y": -537.3971539884709,
        "z": null,
        "alpha": null,
        "beta": null,
        "gamma": null,
        "t": 1540293521178,
        "stroke_id": 0
      },
      {
        "x": -428.7416695024979,
        "y": -524.5918230702903,
        "z": null,
        "alpha": null,
        "beta": null,
        "gamma": null,
        "t": 1540293521195,
        "stroke_id": 0
      },
      {
        "x": -430.54910734543853,
        "y": -520.5977019247467,
        "z": null,
        "alpha": null,
        "beta": null,
        "gamma": null,
        "t": 1540293521211,
        "stroke_id": 0
      },
      {
        "x": -434.43217278790223,
        "y": -511.64507937317467,
        "z": null,
        "alpha": null,
        "beta": null,
        "gamma": null,
        "t": 1540293521228,
        "stroke_id": 0
      },
      {
        "x": -436.88110162352507,
        "y": -507.83002837883305,
        "z": null,
        "alpha": null,
        "beta": null,
        "gamma": null,
        "t": 1540293521245,
        "stroke_id": 0
      },
      {
        "x": -439.3160726942851,
        "y": -501.5878669510155,
        "z": null,
        "alpha": null,
        "beta": null,
        "gamma": null,
        "t": 1540293521261,
        "stroke_id": 0
      },
      {
        "x": -441.3170635856988,
        "y": -499.3774840410084,
        "z": null,
        "alpha": null,
        "beta": null,
        "gamma": null,
        "t": 1540293521279,
        "stroke_id": 0
      },
      {
        "x": -442.8556336356322,
        "y": -496.3465399871169,
        "z": null,
        "alpha": null,
        "beta": null,
        "gamma": null,
        "t": 1540293521294,
        "stroke_id": 0
      },
      {
        "x": -442.8556336356322,
        "y": -496.3465399871169,
        "z": null,
        "alpha": null,
        "beta": null,
        "gamma": null,
        "t": 1540293521311,
        "stroke_id": 0
      },
      {
        "x": -443.3933692216465,
        "y": -494.4201858038127,
        "z": null,
        "alpha": null,
        "beta": null,
        "gamma": null,
        "t": 1540293521329,
        "stroke_id": 0
      },
      {
        "x": -444.21513353436353,
        "y": -493.95708692590784,
        "z": null,
        "alpha": null,
        "beta": null,
        "gamma": null,
        "t": 1540293521345,
        "stroke_id": 0
      },
      {
        "x": -444.85662452704594,
        "y": -494.13615707710983,
        "z": null,
        "alpha": null,
        "beta": null,
        "gamma": null,
        "t": 1540293521362,
        "stroke_id": 0
      },
      {
        "x": -444.3565463132986,
        "y": -494.6890535968198,
        "z": null,
        "alpha": null,
        "beta": null,
        "gamma": null,
        "t": 1540293521419,
        "stroke_id": 0
      }
    ]
    }
  },
  "device": {
    "osBrowserInfo": "5.0 (Linux; Android 7.0; SM-T580 Build/NRD90M) AppleWebKit/537.36 (KHTML, like Gecko) Chrome/64.0.3282.137 Safari/537.36",
    "resolutionHeight": 1280,
    "resolutionWidth": 800,
    "windowHeight": 1160,
    "windowWidth": 800,
    "pixelRatio": 1.5,
    "mouse": false,
    "pen": false,
    "finger": true,
    "acceleration": false,
    "webcam": false
  }
}