{
  "name": "N",
  "subject": 9,
  "date": null,
  "paths": {
    "Finger": {
      "strokes":
    [
      {
        "x": 702.4313594990081,
        "y": -49.317834275814164,
        "z": null,
        "alpha": null,
        "beta": null,
        "gamma": null,
        "t": 1540822575571,
        "stroke_id": 0
      },
      {
        "x": 703.0332345187923,
        "y": -49.032661918626445,
        "z": null,
        "alpha": null,
        "beta": null,
        "gamma": null,
        "t": 1540822575584,
        "stroke_id": 0
      },
      {
        "x": 720.4105770059024,
        "y": -45.22543426606603,
        "z": null,
        "alpha": null,
        "beta": null,
        "gamma": null,
        "t": 1540822575600,
        "stroke_id": 0
      },
      {
        "x": 737.1689324324267,
        "y": -42.44955896633536,
        "z": null,
        "alpha": null,
        "beta": null,
        "gamma": null,
        "t": 1540822575617,
        "stroke_id": 0
      },
      {
        "x": 761.3793318694318,
        "y": -39.831055748720075,
        "z": null,
        "alpha": null,
        "beta": null,
        "gamma": null,
        "t": 1540822575634,
        "stroke_id": 0
      },
      {
        "x": 763.1547272793534,
        "y": -40.464925447318535,
        "z": null,
        "alpha": null,
        "beta": null,
        "gamma": null,
        "t": 1540822575651,
        "stroke_id": 0
      },
      {
        "x": 749.583954602416,
        "y": -47.63291931640492,
        "z": null,
        "alpha": null,
        "beta": null,
        "gamma": null,
        "t": 1540822575668,
        "stroke_id": 0
      },
      {
        "x": 736.0131819254786,
        "y": -54.80091318549131,
        "z": null,
        "alpha": null,
        "beta": null,
        "gamma": null,
        "t": 1540822575684,
        "stroke_id": 0
      },
      {
        "x": 692.6038251170027,
        "y": -76.84361673747861,
        "z": null,
        "alpha": null,
        "beta": null,
        "gamma": null,
        "t": 1540822575701,
        "stroke_id": 0
      },
      {
        "x": 665.4929737859641,
        "y": -89.68891704951193,
        "z": null,
        "alpha": null,
        "beta": null,
        "gamma": null,
        "t": 1540822575717,
        "stroke_id": 0
      },
      {
        "x": 604.009716090129,
        "y": -120.29515414285473,
        "z": null,
        "alpha": null,
        "beta": null,
        "gamma": null,
        "t": 1540822575736,
        "stroke_id": 0
      },
      {
        "x": 569.6693044041468,
        "y": -136.56586787143027,
        "z": null,
        "alpha": null,
        "beta": null,
        "gamma": null,
        "t": 1540822575751,
        "stroke_id": 0
      },
      {
        "x": 502.79587112091826,
        "y": -168.25094197444582,
        "z": null,
        "alpha": null,
        "beta": null,
        "gamma": null,
        "t": 1540822575769,
        "stroke_id": 0
      },
      {
        "x": 474.33780105702584,
        "y": -181.3660676322487,
        "z": null,
        "alpha": null,
        "beta": null,
        "gamma": null,
        "t": 1540822575785,
        "stroke_id": 0
      },
      {
        "x": 436.3826091935718,
        "y": -199.34948806909537,
        "z": null,
        "alpha": null,
        "beta": null,
        "gamma": null,
        "t": 1540822575803,
        "stroke_id": 0
      },
      {
        "x": 427.77383542696003,
        "y": -204.5349498841411,
        "z": null,
        "alpha": null,
        "beta": null,
        "gamma": null,
        "t": 1540822575820,
        "stroke_id": 0
      },
      {
        "x": 425.3325756396257,
        "y": -207.1666986481983,
        "z": null,
        "alpha": null,
        "beta": null,
        "gamma": null,
        "t": 1540822575836,
        "stroke_id": 0
      },
      {
        "x": 439.3798459330462,
        "y": -205.67535337967107,
        "z": null,
        "alpha": null,
        "beta": null,
        "gamma": null,
        "t": 1540822575851,
        "stroke_id": 0
      },
      {
        "x": 459.38893718421355,
        "y": -204.30938551444487,
        "z": null,
        "alpha": null,
        "beta": null,
        "gamma": null,
        "t": 1540822575870,
        "stroke_id": 0
      },
      {
        "x": 517.4178674988513,
        "y": -195.9961273774884,
        "z": null,
        "alpha": null,
        "beta": null,
        "gamma": null,
        "t": 1540822575885,
        "stroke_id": 0
      },
      {
        "x": 551.5049230662753,
        "y": -191.64812681759537,
        "z": null,
        "alpha": null,
        "beta": null,
        "gamma": null,
        "t": 1540822575903,
        "stroke_id": 0
      },
      {
        "x": 620.6006775688655,
        "y": -181.77953405448312,
        "z": null,
        "alpha": null,
        "beta": null,
        "gamma": null,
        "t": 1540822575919,
        "stroke_id": 0
      },
      {
        "x": 653.3725090822501,
        "y": -176.2111357876258,
        "z": null,
        "alpha": null,
        "beta": null,
        "gamma": null,
        "t": 1540822575935,
        "stroke_id": 0
      },
      {
        "x": 711.2584350770077,
        "y": -167.5960576260854,
        "z": null,
        "alpha": null,
        "beta": null,
        "gamma": null,
        "t": 1540822575952,
        "stroke_id": 0
      },
      {
        "x": 733.6614444252768,
        "y": -165.83390776260575,
        "z": null,
        "alpha": null,
        "beta": null,
        "gamma": null,
        "t": 1540822575968,
        "stroke_id": 0
      },
      {
        "x": 766.2912508679642,
        "y": -166.9722097931595,
        "z": null,
        "alpha": null,
        "beta": null,
        "gamma": null,
        "t": 1540822575985,
        "stroke_id": 0
      },
      {
        "x": 775.0278249096483,
        "y": -169.84066700837866,
        "z": null,
        "alpha": null,
        "beta": null,
        "gamma": null,
        "t": 1540822576002,
        "stroke_id": 0
      },
      {
        "x": 775.0604774308504,
        "y": -182.36702022622893,
        "z": null,
        "alpha": null,
        "beta": null,
        "gamma": null,
        "t": 1540822576019,
        "stroke_id": 0
      },
      {
        "x": 767.5305406739113,
        "y": -192.94265762866814,
        "z": null,
        "alpha": null,
        "beta": null,
        "gamma": null,
        "t": 1540822576036,
        "stroke_id": 0
      },
      {
        "x": 731.5268654348665,
        "y": -224.38682035056928,
        "z": null,
        "alpha": null,
        "beta": null,
        "gamma": null,
        "t": 1540822576054,
        "stroke_id": 0
      },
      {
        "x": 706.5568974891669,
        "y": -241.75059588444236,
        "z": null,
        "alpha": null,
        "beta": null,
        "gamma": null,
        "t": 1540822576069,
        "stroke_id": 0
      },
      {
        "x": 644.520085712963,
        "y": -277.41495889116413,
        "z": null,
        "alpha": null,
        "beta": null,
        "gamma": null,
        "t": 1540822576087,
        "stroke_id": 0
      },
      {
        "x": 610.1950210383989,
        "y": -292.9403289066699,
        "z": null,
        "alpha": null,
        "beta": null,
        "gamma": null,
        "t": 1540822576105,
        "stroke_id": 0
      },
      {
        "x": 541.6562227371317,
        "y": -318.7750560664099,
        "z": null,
        "alpha": null,
        "beta": null,
        "gamma": null,
        "t": 1540822576120,
        "stroke_id": 0
      },
      {
        "x": 509.24987919916447,
        "y": -328.22805985650865,
        "z": null,
        "alpha": null,
        "beta": null,
        "gamma": null,
        "t": 1540822576137,
        "stroke_id": 0
      },
      {
        "x": 482.24905826000884,
        "y": -335.8568829238648,
        "z": null,
        "alpha": null,
        "beta": null,
        "gamma": null,
        "t": 1540822576153,
        "stroke_id": 0
      },
      {
        "x": 447.1943182905883,
        "y": -343.6135062662934,
        "z": null,
        "alpha": null,
        "beta": null,
        "gamma": null,
        "t": 1540822576169,
        "stroke_id": 0
      },
      {
        "x": 440.02743284800306,
        "y": -344.05801573741985,
        "z": null,
        "alpha": null,
        "beta": null,
        "gamma": null,
        "t": 1540822576186,
        "stroke_id": 0
      }
    ]
    }
  },
  "device": {
    "osBrowserInfo": "5.0 (Linux; Android 7.0; SM-T580 Build/NRD90M) AppleWebKit/537.36 (KHTML, like Gecko) Chrome/64.0.3282.137 Safari/537.36",
    "resolutionHeight": 1280,
    "resolutionWidth": 800,
    "windowHeight": 1160,
    "windowWidth": 800,
    "pixelRatio": 1.5,
    "mouse": false,
    "pen": false,
    "finger": true,
    "acceleration": false,
    "webcam": false
  }
}